{
  "Z": 0.5736380219459534,
  "Z_stock_gap": 0.0,
  "Z_stock_validation": 0.5736380219459534,
  "backward_attempted_scales": "4096",
  "backward_retry_count": 0,
  "backward_scale": 4096.0,
  "backward_scale_initial": 65536.0,
  "backward_scale_reductions_total": 4,
  "best_Z_so_far": 0.4692862033843994,
  "best_iter_so_far": 717,
  "bspline_enabled": 0,
  "bspline_grad_norm": 0.0,
  "bspline_max_disp": 0.0,
  "bspline_mean_disp": 0.0,
  "bspline_num_at_max": 0,
  "bspline_num_at_min": 0,
  "bspline_p95_disp": 0.0,
  "bspline_param_max": 0.0,
  "bspline_param_mean_abs": 0.0,
  "bspline_param_min": 0.0,
  "case_id": "face_002__add_black_sunglasses",
  "clean_edit_embedding_norm": 1.0,
  "combined_max_disp_px": 19.175535202026367,
  "combined_mean_disp_px": 9.11544418334961,
  "combined_p95_disp_px": 14.382914543151855,
  "components_at_boundary": "differential_surface,lens_barrel,tps",
  "dct_clipped_high_fraction": 0.0,
  "dct_clipped_low_fraction": 0.0,
  "dct_coefficient_delta_l1": 0.0,
  "dct_coefficient_delta_l2": 0.0,
  "dct_dc_energy": 0.0,
  "dct_enabled": 0,
  "dct_frequency_mask_mode": "all_ac",
  "dct_gain_grad_norm": 0.0,
  "dct_gain_l2": 0.0,
  "dct_gain_max": 0.0,
  "dct_gain_mean": 0.0,
  "dct_gain_mean_abs": 0.0,
  "dct_gain_min": 0.0,
  "dct_high_frequency_energy_after": 0.0,
  "dct_high_frequency_energy_before": 0.0,
  "dct_input_coefficient_energy": 0.0,
  "dct_low_frequency_energy_after": 0.0,
  "dct_low_frequency_energy_before": 0.0,
  "dct_mid_frequency_energy_after": 0.0,
  "dct_mid_frequency_energy_before": 0.0,
  "dct_num_at_max": 0,
  "dct_num_at_min": 0,
  "dct_num_clamped": 0,
  "dct_output_coefficient_energy": 0.0,
  "dct_relative_energy_change": 0.0,
  "dct_selected_frequency_count": 0,
  "dct_spatial_delta_l1": 0.0,
  "dct_spatial_delta_l2": 0.0,
  "dct_spatial_delta_max_abs": 0.0,
  "dct_spatial_delta_mse": 0.0,
  "delaunay_enabled": 1,
  "delaunay_grad_norm": 0.12159156054258347,
  "delaunay_max_disp": 9.933728218078613,
  "delaunay_mean_disp": 2.885850191116333,
  "delaunay_num_at_max": 0,
  "delaunay_num_at_min": 0,
  "delaunay_p95_disp": 6.649783611297607,
  "delaunay_param_max": 5.621699810028076,
  "delaunay_param_mean_abs": 1.4647303819656372,
  "delaunay_param_min": -7.177086353302002,
  "differential_surface_enabled": 1,
  "differential_surface_grad_norm": 15.429900169372559,
  "differential_surface_max_disp": 5.199646472930908,
  "differential_surface_mean_disp": 2.1541786193847656,
  "differential_surface_num_at_max": 10,
  "differential_surface_num_at_min": 10,
  "differential_surface_p95_disp": 4.266670227050781,
  "differential_surface_param_max": 0.019999999552965164,
  "differential_surface_param_mean_abs": 0.009303571656346321,
  "differential_surface_param_min": -0.019999999552965164,
  "edit_identity_angle_degrees": 54.99569320678711,
  "edit_identity_angle_radians": 0.9598559141159058,
  "edit_identity_cosine_distance": 0.42636197805404663,
  "edit_identity_cosine_similarity_raw": 0.5736380219459534,
  "edit_identity_l2_embedding_distance": 0.9234305024147034,
  "edit_identity_similarity_score_pct": 57.36380386352539,
  "editor_forward": "exact_installed_diffusers_pipeline_body",
  "editor_num_inference_steps": 20,
  "face_id": "face_002",
  "fft_phase_enabled": 0,
  "fft_phase_grad_norm": 0.0,
  "fft_phase_max_abs": 0.0,
  "fft_phase_mean_abs": 0.0,
  "fft_phase_norm": 0.0,
  "fft_phase_num_at_max": 0,
  "fft_phase_num_at_min": 0,
  "fft_phase_num_clamped": 0,
  "fft_spatial_delta_mse": 0.0,
  "foldover_fraction": 0.0,
  "fraction_clamped_total": 0.14473684210526316,
  "geodesic_enabled": 0,
  "geodesic_grad_norm": 0.0,
  "geodesic_max_disp": 0.0,
  "geodesic_mean_disp": 0.0,
  "geodesic_num_at_max": 0,
  "geodesic_num_at_min": 0,
  "geodesic_p95_disp": 0.0,
  "geodesic_param_max": 0.0,
  "geodesic_param_mean_abs": 0.0,
  "geodesic_param_min": 0.0,
  "identity_angle_degrees": 54.99569320678711,
  "identity_angle_radians": 0.9598559141159058,
  "identity_cosine_distance": 0.42636197805404663,
  "identity_cosine_similarity_raw": 0.5736380219459534,
  "identity_l2_embedding_distance": 0.9234305024147034,
  "identity_similarity_score_pct": 57.36380386352539,
  "input_identity_angle_degrees": 52.05093002319336,
  "input_identity_angle_radians": 0.9084600806236267,
  "input_identity_cosine_distance": 0.38503921031951904,
  "input_identity_cosine_similarity_raw": 0.614960789680481,
  "input_identity_l2_embedding_distance": 0.8775411248207092,
  "input_identity_left_embedding_norm": 1.0,
  "input_identity_right_embedding_norm": 0.9999999403953552,
  "input_identity_similarity_score_pct": 61.49607849121094,
  "iter": 750,
  "jacobian_det_min": 0.666964590549469,
  "l2_to_original": 0.11908615380525589,
  "laplacian_enabled": 0,
  "laplacian_grad_norm": 0.0,
  "laplacian_max_disp": 0.0,
  "laplacian_mean_disp": 0.0,
  "laplacian_num_at_max": 0,
  "laplacian_num_at_min": 0,
  "laplacian_p95_disp": 0.0,
  "laplacian_param_max": 0.0,
  "laplacian_param_mean_abs": 0.0,
  "laplacian_param_min": 0.0,
  "learning_rate": 0.1,
  "legacy_fft_strength_equivalent": 0.0,
  "lens_barrel_enabled": 1,
  "lens_barrel_grad_norm": 1.0197982788085938,
  "lens_barrel_max_disp": 17.878252029418945,
  "lens_barrel_mean_disp": 4.092961311340332,
  "lens_barrel_num_at_max": 0,
  "lens_barrel_num_at_min": 1,
  "lens_barrel_p95_disp": 11.223423957824707,
  "lens_barrel_param_max": -0.029999999329447746,
  "lens_barrel_param_mean_abs": 0.029999999329447746,
  "lens_barrel_param_min": -0.029999999329447746,
  "lens_pincushion_enabled": 0,
  "lens_pincushion_grad_norm": 0.0,
  "lens_pincushion_max_disp": 0.0,
  "lens_pincushion_mean_disp": 0.0,
  "lens_pincushion_num_at_max": 0,
  "lens_pincushion_num_at_min": 0,
  "lens_pincushion_p95_disp": 0.0,
  "lens_pincushion_param_max": 0.0,
  "lens_pincushion_param_mean_abs": 0.0,
  "lens_pincushion_param_min": 0.0,
  "loss": 0.5736380219459534,
  "mobius_enabled": 0,
  "mobius_grad_norm": 0.0,
  "mobius_max_disp": 0.0,
  "mobius_mean_disp": 0.0,
  "mobius_num_at_max": 0,
  "mobius_num_at_min": 0,
  "mobius_p95_disp": 0.0,
  "mobius_param_max": 0.0,
  "mobius_param_mean_abs": 0.0,
  "mobius_param_min": 0.0,
  "mse_to_original": 0.014181512407958508,
  "num_at_max_total": 11,
  "num_at_min_total": 11,
  "num_clamped_total": 22,
  "num_total_params": 152,
  "optimizer_updates_completed": 750,
  "original_embedding_norm": 1.0,
  "peak_vram_gb": 15.502204418182373,
  "perturbed_edit_embedding_norm": 1.0,
  "perturbed_embedding_norm": 1.0,
  "phase": "optimization",
  "polar_enabled": 0,
  "polar_grad_norm": 0.0,
  "polar_max_disp": 0.0,
  "polar_mean_disp": 0.0,
  "polar_p95_disp": 0.0,
  "polar_radial_num_at_max": 0,
  "polar_radial_num_at_min": 0,
  "polar_radial_param_max": 0.0,
  "polar_radial_param_mean_abs": 0.0,
  "polar_radial_param_min": 0.0,
  "polar_twist_num_at_max": 0,
  "polar_twist_num_at_min": 0,
  "polar_twist_param_max": 0.0,
  "polar_twist_param_mean_abs": 0.0,
  "polar_twist_param_min": 0.0,
  "prompt": "add black sunglasses",
  "psnr_to_original": 18.482774507181706,
  "rolling_enabled": 1,
  "rolling_grad_norm": 0.17620238661766052,
  "rolling_max_disp": 1.0007281303405762,
  "rolling_mean_disp": 0.6846308708190918,
  "rolling_num_at_max": 0,
  "rolling_num_at_min": 0,
  "rolling_p95_disp": 0.9983953237533569,
  "rolling_param_max": -0.6043030619621277,
  "rolling_param_mean_abs": 0.6375534534454346,
  "rolling_param_min": -0.6708038449287415,
  "seconds_elapsed": 4074.346840072423,
  "seconds_iter": 6.677539940923452,
  "seed": 250852,
  "smoothness_tv": 0.14804258942604065,
  "ssim_to_original": 0.5293283462524414,
  "total_geometry_grad_norm": 15.465579986572266,
  "total_grad_norm": 15.465579986572266,
  "tps_enabled": 1,
  "tps_grad_norm": 0.12846378982067108,
  "tps_max_disp": 5.546041965484619,
  "tps_mean_disp": 2.3784546852111816,
  "tps_num_at_max": 1,
  "tps_num_at_min": 0,
  "tps_p95_disp": 5.042437553405762,
  "tps_param_max": 4.0960001945495605,
  "tps_param_mean_abs": 1.0273858308792114,
  "tps_param_min": -4.063360691070557
}
