{
  "Z": 0.8008335828781128,
  "Z_stock_gap": 0.0,
  "Z_stock_validation": 0.8008335828781128,
  "backward_attempted_scales": "16384",
  "backward_retry_count": 0,
  "backward_scale": 16384.0,
  "backward_scale_initial": 65536.0,
  "backward_scale_reductions_total": 2,
  "best_Z_so_far": 0.7727760076522827,
  "best_iter_so_far": 261,
  "bspline_enabled": 0,
  "bspline_grad_norm": 0.0,
  "bspline_max_disp": 0.0,
  "bspline_mean_disp": 0.0,
  "bspline_num_at_max": 0,
  "bspline_num_at_min": 0,
  "bspline_p95_disp": 0.0,
  "bspline_param_max": 0.0,
  "bspline_param_mean_abs": 0.0,
  "bspline_param_min": 0.0,
  "case_id": "face_002__add_headphones",
  "clean_edit_embedding_norm": 1.0,
  "combined_max_disp_px": 5.864116668701172,
  "combined_mean_disp_px": 2.2365195751190186,
  "combined_p95_disp_px": 4.139685153961182,
  "components_at_boundary": "",
  "dct_clipped_high_fraction": 0.0,
  "dct_clipped_low_fraction": 0.0,
  "dct_coefficient_delta_l1": 0.0,
  "dct_coefficient_delta_l2": 0.0,
  "dct_dc_energy": 0.0,
  "dct_enabled": 0,
  "dct_frequency_mask_mode": "all_ac",
  "dct_gain_grad_norm": 0.0,
  "dct_gain_l2": 0.0,
  "dct_gain_max": 0.0,
  "dct_gain_mean": 0.0,
  "dct_gain_mean_abs": 0.0,
  "dct_gain_min": 0.0,
  "dct_high_frequency_energy_after": 0.0,
  "dct_high_frequency_energy_before": 0.0,
  "dct_input_coefficient_energy": 0.0,
  "dct_low_frequency_energy_after": 0.0,
  "dct_low_frequency_energy_before": 0.0,
  "dct_mid_frequency_energy_after": 0.0,
  "dct_mid_frequency_energy_before": 0.0,
  "dct_num_at_max": 0,
  "dct_num_at_min": 0,
  "dct_num_clamped": 0,
  "dct_output_coefficient_energy": 0.0,
  "dct_relative_energy_change": 0.0,
  "dct_selected_frequency_count": 0,
  "dct_spatial_delta_l1": 0.0,
  "dct_spatial_delta_l2": 0.0,
  "dct_spatial_delta_max_abs": 0.0,
  "dct_spatial_delta_mse": 0.0,
  "delaunay_enabled": 1,
  "delaunay_grad_norm": 0.06342367827892303,
  "delaunay_max_disp": 2.824885606765747,
  "delaunay_mean_disp": 0.9921129941940308,
  "delaunay_num_at_max": 0,
  "delaunay_num_at_min": 0,
  "delaunay_p95_disp": 2.3563790321350098,
  "delaunay_param_max": 1.9588091373443604,
  "delaunay_param_mean_abs": 0.7402764558792114,
  "delaunay_param_min": -2.7031893730163574,
  "differential_surface_enabled": 0,
  "differential_surface_grad_norm": 0.0,
  "differential_surface_max_disp": 0.0,
  "differential_surface_mean_disp": 0.0,
  "differential_surface_num_at_max": 0,
  "differential_surface_num_at_min": 0,
  "differential_surface_p95_disp": 0.0,
  "differential_surface_param_max": 0.0,
  "differential_surface_param_mean_abs": 0.0,
  "differential_surface_param_min": 0.0,
  "edit_identity_angle_degrees": 36.790218353271484,
  "edit_identity_angle_radians": 0.6421104669570923,
  "edit_identity_cosine_distance": 0.1991664171218872,
  "edit_identity_cosine_similarity_raw": 0.8008335828781128,
  "edit_identity_l2_embedding_distance": 0.6311361789703369,
  "edit_identity_similarity_score_pct": 80.08335876464844,
  "editor_forward": "exact_installed_diffusers_pipeline_body",
  "editor_num_inference_steps": 20,
  "face_id": "face_002",
  "fft_phase_enabled": 0,
  "fft_phase_grad_norm": 0.0,
  "fft_phase_max_abs": 0.0,
  "fft_phase_mean_abs": 0.0,
  "fft_phase_norm": 0.0,
  "fft_phase_num_at_max": 0,
  "fft_phase_num_at_min": 0,
  "fft_phase_num_clamped": 0,
  "fft_spatial_delta_mse": 0.0,
  "foldover_fraction": 0.0,
  "fraction_clamped_total": 0.0,
  "geodesic_enabled": 0,
  "geodesic_grad_norm": 0.0,
  "geodesic_max_disp": 0.0,
  "geodesic_mean_disp": 0.0,
  "geodesic_num_at_max": 0,
  "geodesic_num_at_min": 0,
  "geodesic_p95_disp": 0.0,
  "geodesic_param_max": 0.0,
  "geodesic_param_mean_abs": 0.0,
  "geodesic_param_min": 0.0,
  "identity_angle_degrees": 36.790218353271484,
  "identity_angle_radians": 0.6421104669570923,
  "identity_cosine_distance": 0.1991664171218872,
  "identity_cosine_similarity_raw": 0.8008335828781128,
  "identity_l2_embedding_distance": 0.6311361789703369,
  "identity_similarity_score_pct": 80.08335876464844,
  "input_identity_angle_degrees": 26.424259185791016,
  "input_identity_angle_radians": 0.4611903131008148,
  "input_identity_cosine_distance": 0.10447657108306885,
  "input_identity_cosine_similarity_raw": 0.8955234289169312,
  "input_identity_l2_embedding_distance": 0.45711401104927063,
  "input_identity_left_embedding_norm": 1.0,
  "input_identity_right_embedding_norm": 1.0,
  "input_identity_similarity_score_pct": 89.5523452758789,
  "iter": 300,
  "jacobian_det_min": 0.8120489716529846,
  "l2_to_original": 0.055785827338695526,
  "laplacian_enabled": 0,
  "laplacian_grad_norm": 0.0,
  "laplacian_max_disp": 0.0,
  "laplacian_mean_disp": 0.0,
  "laplacian_num_at_max": 0,
  "laplacian_num_at_min": 0,
  "laplacian_p95_disp": 0.0,
  "laplacian_param_max": 0.0,
  "laplacian_param_mean_abs": 0.0,
  "laplacian_param_min": 0.0,
  "learning_rate": 0.1,
  "legacy_fft_strength_equivalent": 0.0,
  "lens_barrel_enabled": 0,
  "lens_barrel_grad_norm": 0.0,
  "lens_barrel_max_disp": 0.0,
  "lens_barrel_mean_disp": 0.0,
  "lens_barrel_num_at_max": 0,
  "lens_barrel_num_at_min": 0,
  "lens_barrel_p95_disp": 0.0,
  "lens_barrel_param_max": 0.0,
  "lens_barrel_param_mean_abs": 0.0,
  "lens_barrel_param_min": 0.0,
  "lens_pincushion_enabled": 0,
  "lens_pincushion_grad_norm": 0.0,
  "lens_pincushion_max_disp": 0.0,
  "lens_pincushion_mean_disp": 0.0,
  "lens_pincushion_num_at_max": 0,
  "lens_pincushion_num_at_min": 0,
  "lens_pincushion_p95_disp": 0.0,
  "lens_pincushion_param_max": 0.0,
  "lens_pincushion_param_mean_abs": 0.0,
  "lens_pincushion_param_min": 0.0,
  "loss": 0.8008335828781128,
  "mobius_enabled": 0,
  "mobius_grad_norm": 0.0,
  "mobius_max_disp": 0.0,
  "mobius_mean_disp": 0.0,
  "mobius_num_at_max": 0,
  "mobius_num_at_min": 0,
  "mobius_p95_disp": 0.0,
  "mobius_param_max": 0.0,
  "mobius_param_mean_abs": 0.0,
  "mobius_param_min": 0.0,
  "mse_to_original": 0.0031120586208999157,
  "num_at_max_total": 0,
  "num_at_min_total": 0,
  "num_clamped_total": 0,
  "num_total_params": 102,
  "optimizer_updates_completed": 300,
  "original_embedding_norm": 1.0,
  "peak_vram_gb": 15.498905181884766,
  "perturbed_edit_embedding_norm": 1.0,
  "perturbed_embedding_norm": 1.0,
  "phase": "optimization",
  "polar_enabled": 0,
  "polar_grad_norm": 0.0,
  "polar_max_disp": 0.0,
  "polar_mean_disp": 0.0,
  "polar_p95_disp": 0.0,
  "polar_radial_num_at_max": 0,
  "polar_radial_num_at_min": 0,
  "polar_radial_param_max": 0.0,
  "polar_radial_param_mean_abs": 0.0,
  "polar_radial_param_min": 0.0,
  "polar_twist_num_at_max": 0,
  "polar_twist_num_at_min": 0,
  "polar_twist_param_max": 0.0,
  "polar_twist_param_mean_abs": 0.0,
  "polar_twist_param_min": 0.0,
  "prompt": "add headphones",
  "psnr_to_original": 25.069522309324846,
  "rolling_enabled": 1,
  "rolling_grad_norm": 0.02470652014017105,
  "rolling_max_disp": 1.9426908493041992,
  "rolling_mean_disp": 1.1350715160369873,
  "rolling_num_at_max": 0,
  "rolling_num_at_min": 0,
  "rolling_p95_disp": 1.9028738737106323,
  "rolling_param_max": 1.9934849739074707,
  "rolling_param_mean_abs": 1.1861416101455688,
  "rolling_param_min": 0.378798246383667,
  "seconds_elapsed": 1748.6675211004913,
  "seconds_iter": 6.901988996192813,
  "seed": 438717,
  "smoothness_tv": 0.03880670666694641,
  "ssim_to_original": 0.7191223502159119,
  "total_geometry_grad_norm": 0.10657821595668793,
  "total_grad_norm": 0.10657821595668793,
  "tps_enabled": 1,
  "tps_grad_norm": 0.08201183378696442,
  "tps_max_disp": 3.4100887775421143,
  "tps_mean_disp": 0.9809210300445557,
  "tps_num_at_max": 0,
  "tps_num_at_min": 0,
  "tps_p95_disp": 2.1328036785125732,
  "tps_param_max": 2.010571002960205,
  "tps_param_mean_abs": 0.5237717032432556,
  "tps_param_min": -3.3676464557647705
}
